CHANGES.txt
MANIFEST.in
README.txt
setup.cfg
setup.py
w20e/__init__.py
w20e.pycms_news.egg-info/PKG-INFO
w20e.pycms_news.egg-info/SOURCES.txt
w20e.pycms_news.egg-info/dependency_links.txt
w20e.pycms_news.egg-info/not-zip-safe
w20e.pycms_news.egg-info/requires.txt
w20e.pycms_news.egg-info/top_level.txt
w20e/pycms_news/__init__.py
w20e/pycms_news/configure.zcml
w20e/pycms_news/version.txt
w20e/pycms_news/forms/news.xml
w20e/pycms_news/locale/pycms.pot
w20e/pycms_news/locale/nl/LC_MESSAGES/w20e.pycms.mo
w20e/pycms_news/locale/nl/LC_MESSAGES/w20e.pycms.po
w20e/pycms_news/models/__init__.py
w20e/pycms_news/models/configure.zcml
w20e/pycms_news/models/news.py
w20e/pycms_news/templates/news.pt
w20e/pycms_news/templates/newslisting.pt
w20e/pycms_news/templates/newsviewlet.pt
w20e/pycms_news/views/__init__.py
w20e/pycms_news/views/configure.zcml
w20e/pycms_news/views/news.py