Metadata-Version: 1.1
Name: w20e.pycms-news
Version: 1.0.1a
Summary: Pyramid CMS news package
Home-page: UNKNOWN
Author: D.A.Dokter
Author-email: dokter@w20e.com
License: UNKNOWN
Keywords: web pylons pyramid
Platform: UNKNOWN
Classifier: Programming Language :: Python
Classifier: Framework :: Pylons
Classifier: Topic :: Internet :: WWW/HTTP
Classifier: Topic :: Internet :: WWW/HTTP :: WSGI :: Application
